wtforms_hcaptcha/__init__.py
wtforms_hcaptcha/fields.py
wtforms_hcaptcha/validators.py
wtforms_hcaptcha/widgets.py
wtforms_hcaptcha-0.1.3.dist-info/LICENSE
wtforms_hcaptcha-0.1.3.dist-info/WHEEL
wtforms_hcaptcha-0.1.3.dist-info/METADATA
wtforms_hcaptcha-0.1.3.dist-info/RECORD
