Metadata-Version: 2.1
Name: wtforms-hcaptcha
Version: 0.1.3
Summary: Custom WTForms field that handles hCaptcha display and validation.
Home-page: https://github.com/jake-walker/wtforms-hcaptcha
License: GPL-3.0-only
Keywords: captcha,form,hcaptcha
Author: Jake Walker
Author-email: hi@jakew.me
Maintainer: Jake Walker
Maintainer-email: hi@jakew.me
Requires-Python: >=3.6,<4.0
Classifier: Development Status :: 4 - Beta
Classifier: Environment :: Web Environment
Classifier: Intended Audience :: Developers
Classifier: License :: OSI Approved :: GNU General Public License v3 (GPLv3)
Classifier: Operating System :: OS Independent
Classifier: Programming Language :: Python :: 3
Classifier: Programming Language :: Python :: 3.6
Classifier: Programming Language :: Python :: 3.7
Classifier: Programming Language :: Python :: 3.8
Classifier: Topic :: Internet :: WWW/HTTP :: Dynamic Content
Classifier: Topic :: Software Development :: Libraries :: Python Modules
Requires-Dist: markupsafe (>=2.0.0,<3.0.0)
Requires-Dist: wtforms (>=2.3.3,<3.0.0)
Project-URL: Documentation, https://github.com/jake-walker/wtforms-hcaptcha
Project-URL: Repository, https://github.com/jake-walker/wtforms-hcaptcha
